mgjson/__about__.py
mgjson/__init__.py
mgjson/mgjson.py
mgjson-0.1.0b1.dist-info/METADATA
mgjson-0.1.0b1.dist-info/WHEEL
mgjson-0.1.0b1.dist-info/entry_points.txt
mgjson-0.1.0b1.dist-info/license_files/LICENSE
mgjson-0.1.0b1.dist-info/RECORD
