Metadata-Version: 2.1
Name: mgjson
Version: 0.1.0b1
Summary: A nifty library for encoding mgjson documents from python.
Project-URL: Documentation, https://github.com/unknown/python-mgjson#readme
Project-URL: Issues, https://github.com/unknown/python-mgjson/issues
Project-URL: Source, https://github.com/unknown/python-mgjson
Author-email: technocake <robin.garen@gmail.com>
Classifier: Development Status :: 4 - Beta
Classifier: Programming Language :: Python
Classifier: Programming Language :: Python :: 3.10
Classifier: Programming Language :: Python :: 3.11
Classifier: Programming Language :: Python :: 3.7
Classifier: Programming Language :: Python :: 3.8
Classifier: Programming Language :: Python :: 3.9
Classifier: Programming Language :: Python :: Implementation :: CPython
Classifier: Programming Language :: Python :: Implementation :: PyPy
Requires-Python: >=3.7
